easy_exit_calls/__init__.py
easy_exit_calls/classes.py
easy_exit_calls/classes.py~
easy_exit_calls/common/__init__.py
easy_exit_calls/common/meta/__init__.py
easy_exit_calls/common/meta/author/__init__.py
easy_exit_calls/common/meta/author/contributors/CONTRIB_TEMPLATE.json
easy_exit_calls/common/meta/author/contributors/__init__.py
easy_exit_calls/common/meta/author/main/__init__.py
easy_exit_calls/common/meta/author/software_org/__init__.py
easy_exit_calls/common/meta/package/__init__.py
easy_exit_calls/common/meta/package/version/__VERSION__
easy_exit_calls/common/meta/package/version/__init__.py
easy_exit_calls/decorator.py
easy_exit_calls/example_helpers.py
easy_exit_calls/helpers/__init__.py
easy_exit_calls/helpers/decorator.py
easy_exit_calls/helpers/handler_list.py
easy_exit_calls/log_engine.py
easy_exit_calls-1.0.0.dev1.dist-info/LICENSE.md
easy_exit_calls-1.0.0.dev1.dist-info/METADATA
easy_exit_calls-1.0.0.dev1.dist-info/WHEEL
easy_exit_calls-1.0.0.dev1.dist-info/RECORD
