Metadata-Version: 2.3
Name: easy-exit-calls
Version: 1.0.0.dev1
Summary: A Python library for managing exit handlers with enhanced features like decorators, UUID tracking, and LIFO execution.
Author: Taylor B.
Author-email: tayjaybabee@gmail.com
Requires-Python: >=3.12,<4.0
Classifier: Development Status :: 3 - Alpha
Classifier: Intended Audience :: Developers
Classifier: License :: OSI Approved :: MIT License
Classifier: Operating System :: OS Independent
Classifier: Programming Language :: Python :: 3.12
Classifier: Programming Language :: Python :: 3 :: Only
Classifier: Topic :: Software Development :: Libraries :: Python Modules
Classifier: Topic :: Utilities
Classifier: Typing :: Typed
Requires-Dist: inspy-logger (==3.2.3)
Requires-Dist: inspyre-toolbox (>=1.6.0-dev22)
Requires-Dist: pytz (>=2025.1,<2026.0)
